setup.py
src/Bindows/__init__.py
src/Bindows/main.py
src/Bindows.egg-info/PKG-INFO
src/Bindows.egg-info/SOURCES.txt
src/Bindows.egg-info/dependency_links.txt
src/Bindows.egg-info/top_level.txt
src/bindows.egg-info/PKG-INFO
src/bindows.egg-info/SOURCES.txt
src/bindows.egg-info/dependency_links.txt
src/bindows.egg-info/top_level.txt